[
  {
    "date": "2026-08-26",
    "venue": "Place 1604",
    "location": "Dieppe, NB",
    "tickets": "",
    "artist": "The Martin Boys"
  },
  {
    "date": "2026-07-18",
    "venue": "Toyrun",
    "location": "Muniac, NB",
    "tickets": "",
    "artist": "Steve Waylon"
  },
  {
    "date": "2026-07-25",
    "venue": "Neguac Country Fest",
    "location": "Neguac, NB",
    "tickets": ""
  },
  {
    "date": "2026-08-07",
    "venue": "Fredrod",
    "location": "Fredericton, NB",
    "tickets": "",
    "artist": "Steve Waylon"
  },
  {
    "date": "2026-10-17",
    "venue": "Minto Legion",
    "location": "Minto, NB",
    "tickets": "",
    "artist": "Steve Waylon"
  }
]